pysumath.py
pysumath-1.0.0.dist-info/METADATA
pysumath-1.0.0.dist-info/WHEEL
pysumath-1.0.0.dist-info/top_level.txt
pysumath-1.0.0.dist-info/RECORD
