Metadata-Version: 2.1
Name: pysumath
Version: 1.0.0
Summary: Biblioteca matemática BRABA feita pelo Thiaguinho
Author: Thiago Arthur
Classifier: Programming Language :: Python :: 3
Classifier: License :: OSI Approved :: MIT License
Classifier: Operating System :: OS Independent
